{
    "data": [
        {
            "quote": "All our dreams can come true, if we have the courage to pursue them.",
            "author": "Walt Disney"
        },
        {
            "quote": "The secret of getting ahead is getting started.",
            "author": "Mark Twain"
        },
        {
            "quote": "Happiness is a state of mind",
            "author": "Walt Disney"
        },
        {
            "quote": "Only the paranoid survive.",
            "author": "Andy Grove"
        },
        {
            "quote": "Change the world by being yourself",
            "author": "Amy Poehler"
        },
        {
            "quote": "It’s hard to beat a person who never gives up",
            "author": "Babe Ruth"
        },
        {
            "quote": "If people are doubting how far you can go, go so far that you can’t hear them anymore",
            "author": "Michele Ruiz"
        },
        {
            "quote": "Only the gentle are really strong",
            "author": "James Dean"
        },
        {
            "quote": "Stay Hungry, Stay Foolish",
            "author": "Steve Jobs"
        },
        {
            "quote": "Write it. Shoot it. Publish it. Crochet it, sauté it, whatever. MAKE",
            "author": "Joss Whedon"
        }
    ]
}
